email_auth_remote/__init__.py
email_auth_remote/admin.py
email_auth_remote/apps.py
email_auth_remote/authentication.py
email_auth_remote/context_processors.py
email_auth_remote/middleware.py
email_auth_remote/models.py
email_auth_remote/permissions.py
email_auth_remote/schema.py
email_auth_remote/settings.py
email_auth_remote/urls.py
email_auth_remote/utils.py
email_auth_remote/views.py
email_auth_remote-1.3.0.dist-info/METADATA
email_auth_remote-1.3.0.dist-info/WHEEL
email_auth_remote-1.3.0.dist-info/top_level.txt
email_auth_remote-1.3.0.dist-info/RECORD
