Metadata-Version: 2.1
Name: email-auth-remote
Version: 1.3.0
Summary: Django app for an endpoint authentication.
Classifier: Programming Language :: Python :: 3
Classifier: Programming Language :: Python :: 3.10
Classifier: Programming Language :: Python :: 3.11
Classifier: Programming Language :: Python :: 3.12
Classifier: Programming Language :: Python :: 3 :: Only
Requires-Python: >=3.11
Requires-Dist: Django >=4.2
Requires-Dist: requests >=2.31
Requires-Dist: djangorestframework >=3.14
Requires-Dist: dj-rest-auth ==5.1.0
Requires-Dist: djangorestframework-simplejwt ==5.3.1
